{"name": "Doki Doki Star Commander", "version": "1.0", "location": {"callable": {"AnimatedMask.render": ["game/effects.rpy", 365], "hide_windows_enabled": ["game/effects.rpy", 37], "game_menu_check": ["game/options.rpy", 132], "Shield.buy": ["game/equipment.rpy", 23], "ParticleBurst.update": ["game/effects.rpy", 208], "doshieldpower": ["game/shipstats.rpy", 95], "Engine.equip": ["game/equipment.rpy", 39], "FinishEnterName": ["game/screens.rpy", 421], "force_integer_multiplier": ["game/options.rpy", 137], "filter_text_tags": ["game/screens.rpy", 1130], "Poem.__init__": ["game/poems.rpy", 14], "specialdamage": ["game/shipstats.rpy", 53], "unenpwr": ["game/shipstats.rpy", 90], "unshpwr": ["game/shipstats.rpy", 75], "Weapon.equip": ["game/weapons.rpy", 21], "Blood.add_burst": ["game/effects.rpy", 254], "delete_character": ["game/definitions.rpy", 36], "TearPiece.update": ["game/effects.rpy", 67], "Ship.equipall": ["game/shipselection.rpy", 28], "monika_alpha": ["game/effects.rpy", 409], "invert": ["game/effects.rpy", 14], "Invert.__init__": ["game/effects.rpy", 23], "damage": ["game/shipstats.rpy", 41], "glitchtext": ["game/glitchtext.rpy", 13], "Tear.render": ["game/effects.rpy", 101], "screenshot_srf": ["game/effects.rpy", 8], "Shield.__init__": ["game/equipment.rpy", 9], "Ship.__init__": ["game/shipselection.rpy", 9], "delete_all_saves": ["game/definitions.rpy", 31], "RectStatic.add": ["game/effects.rpy", 158], "Invert.render": ["game/effects.rpy", 30], "Blood.add_squirt": ["game/effects.rpy", 247], "RigMouse": ["game/screens.rpy", 320], "ehealth": ["game/weapons.rpy", 9], "Engine.__init__": ["game/equipment.rpy", 32], "Blood.__init__": ["game/effects.rpy", 225], "replace_text": ["game/options.rpy", 126], "dounpower": ["game/shipstats.rpy", 128], "ParticleBurst.add": ["game/effects.rpy", 197], "Blood.update": ["game/effects.rpy", 269], "dynbg": ["game/definitions.rpy", 218], "Blood.add_drip": ["game/effects.rpy", 261], "pause": ["game/definitions.rpy", 65], "ParticleBurst.__init__": ["game/effects.rpy", 180], "wppwr": ["game/shipstats.rpy", 80], "unwppwr": ["game/shipstats.rpy", 83], "restore_relevant_characters": ["game/definitions.rpy", 53], "restore_all_characters": ["game/definitions.rpy", 42], "get_pos": ["game/definitions.rpy", 25], "Tear.__init__": ["game/effects.rpy", 78], "Weapon.__init__": ["game/weapons.rpy", 14], "Ship.changeship": ["game/shipselection.rpy", 21], "shpwr": ["game/shipstats.rpy", 71], "Shield.equip": ["game/equipment.rpy", 16], "Weapon.buy": ["game/weapons.rpy", 30], "yuripupils_function": ["game/transforms.rpy", 522], "FileActionMod": ["game/screens.rpy", 792], "damagehull": ["game/shipstats.rpy", 65], "doenginepower": ["game/shipstats.rpy", 117], "Engine.buy": ["game/equipment.rpy", 45], "AnimatedMask.__init__": ["game/effects.rpy", 350], "RectStatic.update": ["game/effects.rpy", 166], "RectStatic.__init__": ["game/effects.rpy", 143], "TearPiece.__init__": ["game/effects.rpy", 58], "enpwr": ["game/shipstats.rpy", 87], "doweaponpower": ["game/shipstats.rpy", 106]}, "screen": {"load": ["game/screens.rpy", 785], "fake_skip_indicator": ["game/screens.rpy", 1508], "say": ["game/screens.rpy", 151], "notify": ["game/screens.rpy", 1567], "enemystats": ["game/stathud.rpy", 16], "rigged_choice": ["game/screens.rpy", 326], "poem": ["game/poems.rpy", 59], "game_menu_m": ["game/screens.rpy", 597], "preferences": ["game/screens.rpy", 921], "confirm": ["game/screens.rpy", 1438], "invert": ["game/effects.rpy", 45], "playerstats": ["game/stathud.rpy", 6], "input": ["game/screens.rpy", 246], "save": ["game/screens.rpy", 778], "skip_indicator": ["game/screens.rpy", 1511], "file_slots": ["game/screens.rpy", 802], "choice": ["game/screens.rpy", 285], "game_menu": ["game/screens.rpy", 602], "name_input": ["game/screens.rpy", 1367], "main_menu": ["game/screens.rpy", 504], "nvl": ["game/screens.rpy", 1605], "quick_menu": ["game/screens.rpy", 367], "about": ["game/screens.rpy", 734], "tear": ["game/effects.rpy", 113], "nvl_dialogue": ["game/screens.rpy", 1637], "dialog": ["game/screens.rpy", 1403], "navigation": ["game/screens.rpy", 427], "history": ["game/screens.rpy", 1107]}, "define": {"n_appeal": ["game/definitions.rpy", 1473], "audio.explosion1": ["game/definitions.rpy", 117], "gui.accent_color": ["game/gui.rpy", 17], "gui.interface_text_size": ["game/gui.rpy", 63], "build.name": ["game/options.rpy", 23], "gui.bar_tile": ["game/gui.rpy", 295], "engine": ["game/shipstats.rpy", 32], "gui.notify_text_size": ["game/gui.rpy", 69], "gui.nvl_thought_xpos": ["game/gui.rpy", 367], "ch4_scene": ["game/definitions.rpy", 1500], "gui.default_font": ["game/gui.rpy", 47], "audio.hlaser": ["game/definitions.rpy", 104], "config.history_length": ["game/gui.rpy", 318], "s_name": ["game/definitions.rpy", 1446], "gui.page_spacing": ["game/gui.rpy", 256], "close_eyes": ["game/transforms.rpy", 362], "gui.page_button_borders": ["game/gui.rpy", 174], "audio.takeoff": ["game/definitions.rpy", 126], "enginepower": ["game/shipstats.rpy", 24], "gui.idle_color": ["game/gui.rpy", 20], "config.enter_transition": ["game/options.rpy", 46], "audio.decloak": ["game/definitions.rpy", 125], "gui.history_text_xalign": ["game/gui.rpy", 335], "basedir": ["game/definitions.rpy", 1441], "dissolve_scene_full": ["game/transforms.rpy", 348], "audio.tnatsuki": ["game/definitions.rpy", 136], "gui.nvl_text_width": ["game/gui.rpy", 362], "gui.slider_tile": ["game/gui.rpy", 297], "gui.text_ypos": ["game/gui.rpy", 121], "audio.t5b": ["game/definitions.rpy", 139], "audio.t5c": ["game/definitions.rpy", 140], "gui.nvl_button_xalign": ["game/gui.rpy", 374], "gui.activate_sound": ["game/gui.rpy", 10], "in_sayori_kill": ["game/definitions.rpy", 1436], "gui.nvl_text_ypos": ["game/gui.rpy", 361], "sayori_confess": ["game/definitions.rpy", 1504], "config.version": ["game/options.rpy", 14], "gui.slot_button_borders": ["game/gui.rpy", 214], "wipeleft": ["game/transforms.rpy", 379], "in_yuri_kill": ["game/definitions.rpy", 1437], "wpbonus": ["game/shipstats.rpy", 25], "gui.skip_ypos": ["game/gui.rpy", 238], "gui.pref_spacing": ["game/gui.rpy", 250], "dissolve_cg": ["game/transforms.rpy", 344], "dissolve_scene": ["game/transforms.rpy", 345], "gui.insensitive_color": ["game/gui.rpy", 33], "audio.t3g2": ["game/definitions.rpy", 92], "audio.t3g3": ["game/definitions.rpy", 93], "m_poemappeal": ["game/definitions.rpy", 1457], "m_appeal": ["game/definitions.rpy", 1476], "config.window_icon": ["game/options.rpy", 97], "gui.notify_ypos": ["game/gui.rpy", 241], "trueblack": ["game/transforms.rpy", 373], "gui.muted_color": ["game/gui.rpy", 37], "gui.button_text_font": ["game/gui.rpy", 147], "background": ["game/definitions.rpy", 1519], "config.has_sound": ["game/options.rpy", 27], "gui.nvl_text_xalign": ["game/gui.rpy", 363], "audio.repair": ["game/definitions.rpy", 121], "gui.slot_button_text_idle_color": ["game/gui.rpy", 217], "y_name": ["game/definitions.rpy", 1449], "natsuki_23": ["game/definitions.rpy", 1507], "gui.scrollbar_tile": ["game/gui.rpy", 296], "gui.game_menu_background": ["game/gui.rpy", 80], "seen_eyes_this_chapter": ["game/definitions.rpy", 1424], "audio.t4g": ["game/definitions.rpy", 96], "allow_skipping": ["game/definitions.rpy", 1440], "gui.history_name_ypos": ["game/gui.rpy", 327], "audio.civile": ["game/definitions.rpy", 100], "n_name": ["game/definitions.rpy", 1448], "gui.nvl_button_xpos": ["game/gui.rpy", 373], "persistent.steam": ["game/definitions.rpy", 8], "gui.name_xalign": ["game/gui.rpy", 101], "config.window": ["game/options.rpy", 62], "ch1_choice": ["game/definitions.rpy", 1491], "config.autosave_slots": ["game/options.rpy", 109], "gui.namebox_borders": ["game/gui.rpy", 110], "rhull": ["game/definitions.rpy", 1513], "config.after_load_transition": ["game/options.rpy", 52], "gui.radio_button_borders": ["game/gui.rpy", 168], "shieldpower": ["game/shipstats.rpy", 22], "config.developer": ["game/definitions.rpy", 10], "audio.ftljump": ["game/definitions.rpy", 127], "gui.vbar_borders": ["game/gui.rpy", 305], "config.end_game_transition": ["game/options.rpy", 56], "config.narrator_menu": ["game/screens.rpy", 338], "poemwinner": ["game/definitions.rpy", 1460], "audio.miss": ["game/definitions.rpy", 115], "gui.quick_button_text_size": ["game/gui.rpy", 177], "help_monika": ["game/definitions.rpy", 1497], "config.mouse": ["game/definitions.rpy", 1439], "gui.quick_button_text_selected_color": ["game/gui.rpy", 180], "y_appeal": ["game/definitions.rpy", 1475], "gui.hover_sound": ["game/gui.rpy", 9], "n": ["game/definitions.rpy", 1407], "bonusdmg": ["game/shipstats.rpy", 12], "m_name": ["game/definitions.rpy", 1447], "audio.hull1": ["game/definitions.rpy", 109], "audio.hull2": ["game/definitions.rpy", 110], "audio.hull3": ["game/definitions.rpy", 111], "gui.history_text_width": ["game/gui.rpy", 334], "audio.t7a": ["game/definitions.rpy", 146], "gui.button_text_size": ["game/gui.rpy", 150], "audio.g1": ["game/definitions.rpy", 159], "wipeleft_scene": ["game/transforms.rpy", 382], "audio.g2": ["game/definitions.rpy", 160], "gui.file_slot_cols": ["game/gui.rpy", 225], "gui.scrollbar_size": ["game/gui.rpy", 291], "gui.about": ["game/options.rpy", 18], "gui.slot_button_width": ["game/gui.rpy", 212], "weaponpower": ["game/shipstats.rpy", 23], "config.has_voice": ["game/options.rpy", 35], "config.rollback_enabled": ["game/options.rpy", 118], "audio.cloak": ["game/definitions.rpy", 124], "credits_ypos": ["game/credits.rpy", 270], "audio.upgrade": ["game/definitions.rpy", 122], "gui.choice_button_borders": ["game/gui.rpy", 196], "gui.nvl_text_xpos": ["game/gui.rpy", 360], "gui.text_xpos": ["game/gui.rpy", 120], "audio.page_turn": ["game/definitions.rpy", 165], "audio.fall": ["game/definitions.rpy", 166], "audio.closet_open": ["game/definitions.rpy", 163], "n_read3": ["game/definitions.rpy", 1487], "y_poemappeal": ["game/definitions.rpy", 1456], "currentpos": ["game/definitions.rpy", 1443], "gui.choice_button_text_xalign": ["game/gui.rpy", 199], "audio.shield3": ["game/definitions.rpy", 114], "gui.history_name_xpos": ["game/gui.rpy", 326], "credits": ["game/shipstats.rpy", 19], "gui.skip_frame_borders": ["game/gui.rpy", 273], "s_poemappeal": ["game/definitions.rpy", 1455], "audio.hb": ["game/definitions.rpy", 161], "maxhp": ["game/shipstats.rpy", 10], "gui.title_text_size": ["game/gui.rpy", 72], "shipsecondary": ["game/shipstats.rpy", 29], "chapter": ["game/definitions.rpy", 1442], "gui.history_height": ["game/gui.rpy", 322], "n_readpoem": ["game/definitions.rpy", 1464], "config.predict_statements": ["game/options.rpy", 117], "audio.t6g": ["game/definitions.rpy", 142], "gui.navigation_xpos": ["game/gui.rpy", 235], "gui.slot_button_height": ["game/gui.rpy", 213], "gui.history_text_ypos": ["game/gui.rpy", 333], "config.nvl_list_length": ["game/screens.rpy", 1658], "currentmode": ["game/definitions.rpy", 1516], "config.name": ["game/options.rpy", 5], "dissolve": ["game/transforms.rpy", 341], "audio.t6s": ["game/definitions.rpy", 144], "audio.t6r": ["game/definitions.rpy", 143], "audio.tyuri": ["game/definitions.rpy", 137], "gui.name_ypos": ["game/gui.rpy", 97], "gui.selected_color": ["game/gui.rpy", 30], "shipclass": ["game/shipstats.rpy", 8], "gui.history_text_xpos": ["game/gui.rpy", 332], "gui.nvl_borders": ["game/gui.rpy", 342], "audio.fire": ["game/definitions.rpy", 116], "dissolve_scene_half": ["game/transforms.rpy", 356], "gui.unscrollable": ["game/gui.rpy", 311], "rshield": ["game/definitions.rpy", 1512], "s_readpoem": ["game/definitions.rpy", 1463], "config.thumbnail_width": ["game/gui.rpy", 221], "audio.t10": ["game/definitions.rpy", 151], "gui.main_menu_background": ["game/gui.rpy", 77], "gui.button_width": ["game/gui.rpy", 136], "gui.button_text_hover_color": ["game/gui.rpy", 154], "gui.nvl_thought_ypos": ["game/gui.rpy", 368], "config.save_directory": ["game/options.rpy", 93], "gui.text_width": ["game/gui.rpy", 124], "gui.namebox_tile": ["game/gui.rpy", 114], "audio.t2g": ["game/definitions.rpy", 87], "y_ranaway": ["game/definitions.rpy", 1484], "gui.hover_color": ["game/gui.rpy", 27], "gui.scrollbar_borders": ["game/gui.rpy", 301], "gui.interface_text_color": ["game/gui.rpy", 42], "audio.civilb": ["game/definitions.rpy", 101], "gui.slot_button_text_size": ["game/gui.rpy", 215], "audio.shipexplode": ["game/definitions.rpy", 118], "n_exclusivewatched": ["game/definitions.rpy", 1479], "gui.idle_small_color": ["game/gui.rpy", 24], "audio.missile": ["game/definitions.rpy", 107], "config.has_autosave": ["game/options.rpy", 103], "gui.navigation_spacing": ["game/gui.rpy", 247], "maxshields": ["game/shipstats.rpy", 35], "audio.t7g": ["game/definitions.rpy", 147], "config.exit_transition": ["game/options.rpy", 47], "gui.button_text_xalign": ["game/gui.rpy", 160], "gui.name_xpos": ["game/gui.rpy", 96], "stealth": ["game/shipstats.rpy", 15], "config.thumbnail_height": ["game/gui.rpy", 222], "gui.name_text_size": ["game/gui.rpy", 60], "y_gave": ["game/definitions.rpy", 1483], "audio.beep": ["game/definitions.rpy", 129], "shields": ["game/shipstats.rpy", 36], "gui.file_slot_rows": ["game/gui.rpy", 226], "gui.button_text_insensitive_color": ["game/gui.rpy", 156], "gui.text_xalign": ["game/gui.rpy", 128], "audio.tsayori": ["game/definitions.rpy", 135], "gui.hover_muted_color": ["game/gui.rpy", 38], "gui.button_text_idle_color": ["game/gui.rpy", 153], "narrator": ["game/definitions.rpy", 1403], "gui.nvl_thought_xalign": ["game/gui.rpy", 370], "gui.nvl_thought_width": ["game/gui.rpy", 369], "ch4_name": ["game/definitions.rpy", 1501], "gui.text_size": ["game/gui.rpy", 57], "hp": ["game/shipstats.rpy", 11], "audio.ghostmenu": ["game/definitions.rpy", 158], "audio.arrive": ["game/definitions.rpy", 128], "gui.choice_button_text_font": ["game/gui.rpy", 197], "y_readpoem": ["game/definitions.rpy", 1465], "gui.button_text_selected_color": ["game/gui.rpy", 155], "shieldgen": ["game/shipstats.rpy", 31], "gui.quick_button_text_idle_color": ["game/gui.rpy", 178], "config.window_show_transition": ["game/options.rpy", 68], "y_read3": ["game/definitions.rpy", 1488], "gui.nvl_height": ["game/gui.rpy", 346], "gui.choice_button_height": ["game/gui.rpy", 194], "gui.frame_tile": ["game/gui.rpy", 279], "config.menu_clear_layers": ["game/options.rpy", 119], "gui.nvl_spacing": ["game/gui.rpy", 350], "quick_menu": ["game/screens.rpy", 397], "y_exclusivewatched": ["game/definitions.rpy", 1480], "gui.name_font": ["game/gui.rpy", 51], "gui.bar_borders": ["game/gui.rpy", 300], "mc": ["game/definitions.rpy", 1404], "dodge": ["game/shipstats.rpy", 37], "config.gl_test_image": ["game/options.rpy", 120], "config.has_music": ["game/options.rpy", 31], "n_poemappeal": ["game/definitions.rpy", 1454], "audio.closet_close": ["game/definitions.rpy", 164], "open_eyes": ["game/transforms.rpy", 368], "gui.textbox_height": ["game/gui.rpy", 88], "audio.hbeam": ["game/definitions.rpy", 106], "gui.text_color": ["game/gui.rpy", 41], "m_readpoem": ["game/definitions.rpy", 1466], "n_poemearly": ["game/definitions.rpy", 1493], "shipname": ["game/shipstats.rpy", 7], "audio.mend": ["game/definitions.rpy", 156], "gui.namebox_height": ["game/gui.rpy", 106], "poemsread": ["game/definitions.rpy", 1469], "gui.textbox_yalign": ["game/gui.rpy", 92], "gui.slot_button_text_hover_color": ["game/gui.rpy", 218], "gui.nvl_name_width": ["game/gui.rpy", 356], "gui.choice_button_text_idle_color": ["game/gui.rpy", 201], "config.main_menu_music": ["game/options.rpy", 40], "gui.button_borders": ["game/gui.rpy", 140], "player": ["game/definitions.rpy", 1417], "audio.t10y": ["game/definitions.rpy", 152], "gui.button_tile": ["game/gui.rpy", 144], "anticheat": ["game/definitions.rpy", 1438], "config.image_cache_size": ["game/options.rpy", 116], "gui.frame_borders": ["game/gui.rpy", 267], "audio.stairs": ["game/definitions.rpy", 130], "audio.tmonika": ["game/definitions.rpy", 134], "sprite": ["game/shipstats.rpy", 9], "gui.choice_button_tile": ["game/gui.rpy", 195], "audio.shield1": ["game/definitions.rpy", 112], "audio.t2": ["game/definitions.rpy", 86], "audio.t3": ["game/definitions.rpy", 90], "audio.t4": ["game/definitions.rpy", 95], "audio.t5": ["game/definitions.rpy", 97], "audio.t6": ["game/definitions.rpy", 141], "consolehistory": ["game/console.rpy", 26], "audio.t8": ["game/definitions.rpy", 148], "audio.t9": ["game/definitions.rpy", 149], "config.layers": ["game/options.rpy", 113], "gui.interface_font": ["game/gui.rpy", 54], "s": ["game/definitions.rpy", 1405], "audio.t3g": ["game/definitions.rpy", 91], "ny": ["game/definitions.rpy", 1409], "audio.t2g3": ["game/definitions.rpy", 89], "audio.t2g2": ["game/definitions.rpy", 88], "shipprimary": ["game/shipstats.rpy", 28], "gui.nvl_name_xalign": ["game/gui.rpy", 357], "gui.label_text_size": ["game/gui.rpy", 66], "tpause": ["game/transforms.rpy", 388], "s_appeal": ["game/definitions.rpy", 1474], "gui.namebox_width": ["game/gui.rpy", 105], "gui.quick_button_text_hover_color": ["game/gui.rpy", 179], "config.allow_skipping": ["game/options.rpy", 100], "audio.t1": ["game/definitions.rpy", 85], "gui.vslider_borders": ["game/gui.rpy", 307], "audio.m1": ["game/definitions.rpy", 155], "gui.slider_borders": ["game/gui.rpy", 302], "audio.shield2": ["game/definitions.rpy", 113], "audio.hcannon": ["game/definitions.rpy", 105], "audio.t9g": ["game/definitions.rpy", 150], "gui.notify_frame_borders": ["game/gui.rpy", 276], "gui.button_height": ["game/gui.rpy", 137], "audio.purchase": ["game/definitions.rpy", 120], "gui.quick_button_text_insensitive_color": ["game/gui.rpy", 181], "shipaugment": ["game/shipstats.rpy", 30], "gui.history_name_width": ["game/gui.rpy", 328], "gui.slot_spacing": ["game/gui.rpy", 259], "gui.pref_button_spacing": ["game/gui.rpy", 253], "gui.confirm_button_text_xalign": ["game/gui.rpy", 172], "config.window_hide_transition": ["game/options.rpy", 69], "audio.t3m": ["game/definitions.rpy", 94], "gui.bar_size": ["game/gui.rpy", 290], "gui.choice_button_width": ["game/gui.rpy", 193], "faint_effect": ["game/definitions.rpy", 1444], "gui.nvl_name_ypos": ["game/gui.rpy", 355], "persistent.demo": ["game/definitions.rpy", 7], "audio.laser1": ["game/definitions.rpy", 103], "audio.t7": ["game/definitions.rpy", 145], "m": ["game/definitions.rpy", 1406], "gui.slot_button_text_xalign": ["game/gui.rpy", 216], "gui.slider_size": ["game/gui.rpy", 292], "gui.confirm_frame_borders": ["game/gui.rpy", 270], "gui.show_name": ["game/options.rpy", 9], "gui.activate_sound_glitch": ["game/gui.rpy", 11], "audio.td": ["game/definitions.rpy", 153], "gui.choice_button_text_hover_color": ["game/gui.rpy", 203], "gui.history_name_xalign": ["game/gui.rpy", 329], "config.autosave_on_quit": ["game/options.rpy", 106], "y": ["game/definitions.rpy", 1408], "help_sayori": ["game/definitions.rpy", 1496], "gui.check_button_borders": ["game/gui.rpy", 170], "ammo": ["game/shipstats.rpy", 18], "gui.choice_spacing": ["game/gui.rpy", 244], "gui.nvl_name_xpos": ["game/gui.rpy", 354], "gui.choice_button_text_size": ["game/gui.rpy", 198], "gui.vscrollbar_borders": ["game/gui.rpy", 306]}, "transform": {"h21": ["game/transforms.rpy", 225], "focus": ["game/transforms.rpy", 41], "h44": ["game/transforms.rpy", 217], "h43": ["game/transforms.rpy", 215], "h42": ["game/transforms.rpy", 213], "h41": ["game/transforms.rpy", 211], "s_kill_bg_start": ["game/cgs.rpy", 314], "f41": ["game/transforms.rpy", 167], "f43": ["game/transforms.rpy", 171], "f42": ["game/transforms.rpy", 169], "f44": ["game/transforms.rpy", 173], "yuripupils_move": ["game/transforms.rpy", 518], "d32": ["game/transforms.rpy", 265], "d33": ["game/transforms.rpy", 267], "d31": ["game/transforms.rpy", 263], "rhide": ["game/transforms.rpy", 113], "menu_fadeout": ["game/splash.rpy", 171], "vignettefade": ["game/transforms.rpy", 447], "malpha": ["game/transforms.rpy", 528], "s44": ["game/transforms.rpy", 195], "s41": ["game/transforms.rpy", 189], "s42": ["game/transforms.rpy", 191], "s43": ["game/transforms.rpy", 193], "d43": ["game/transforms.rpy", 259], "d42": ["game/transforms.rpy", 257], "d41": ["game/transforms.rpy", 255], "dip": ["game/transforms.rpy", 74], "d44": ["game/transforms.rpy", 261], "noise_alpha": ["game/transforms.rpy", 432], "lhide": ["game/transforms.rpy", 108], "menu_bg_move": ["game/splash.rpy", 139], "hopfocus": ["game/transforms.rpy", 68], "tinstant": ["game/transforms.rpy", 37], "paper_in": ["game/poems.rpy", 50], "layerflicker": ["game/transforms.rpy", 468], "credits_text_scroll_right": ["game/credits.rpy", 245], "menu_nav_move": ["game/splash.rpy", 165], "l11": ["game/transforms.rpy", 295], "f22": ["game/transforms.rpy", 183], "f21": ["game/transforms.rpy", 181], "t11": ["game/transforms.rpy", 141], "hf44": ["game/transforms.rpy", 239], "hf42": ["game/transforms.rpy", 235], "hf43": ["game/transforms.rpy", 237], "hf41": ["game/transforms.rpy", 233], "s11": ["game/transforms.rpy", 207], "menu_art_move": ["game/splash.rpy", 177], "hf21": ["game/transforms.rpy", 247], "hf22": ["game/transforms.rpy", 249], "n_cg2_wiggle": ["game/transforms.rpy", 316], "l21": ["game/transforms.rpy", 291], "sh11": ["game/transforms.rpy", 119], "sink": ["game/transforms.rpy", 57], "h11": ["game/transforms.rpy", 229], "leftin": ["game/transforms.rpy", 93], "credits_scroll_left": ["game/credits.rpy", 241], "heartbeat2": ["game/transforms.rpy", 502], "credits_sticker_4": ["game/credits.rpy", 265], "credits_sticker_2": ["game/credits.rpy", 257], "credits_sticker_3": ["game/credits.rpy", 261], "credits_sticker_1": ["game/credits.rpy", 253], "f31": ["game/transforms.rpy", 175], "f32": ["game/transforms.rpy", 177], "f33": ["game/transforms.rpy", 179], "t21": ["game/transforms.rpy", 137], "heartbeat": ["game/transforms.rpy", 499], "t22": ["game/transforms.rpy", 139], "delayed_blink": ["game/screens.rpy", 1529], "t43": ["game/transforms.rpy", 127], "t42": ["game/transforms.rpy", 125], "t41": ["game/transforms.rpy", 123], "hf33": ["game/transforms.rpy", 245], "hf32": ["game/transforms.rpy", 243], "hf31": ["game/transforms.rpy", 241], "t44": ["game/transforms.rpy", 129], "l32": ["game/transforms.rpy", 287], "l33": ["game/transforms.rpy", 289], "l31": ["game/transforms.rpy", 285], "i44": ["game/transforms.rpy", 151], "i42": ["game/transforms.rpy", 147], "i43": ["game/transforms.rpy", 149], "i41": ["game/transforms.rpy", 145], "cgfade": ["game/transforms.rpy", 307], "tcommon": ["game/transforms.rpy", 6], "t32": ["game/transforms.rpy", 133], "t33": ["game/transforms.rpy", 135], "t31": ["game/transforms.rpy", 131], "credits_scroll_right": ["game/credits.rpy", 237], "s31": ["game/transforms.rpy", 197], "s33": ["game/transforms.rpy", 201], "s32": ["game/transforms.rpy", 199], "thide": ["game/transforms.rpy", 102], "noisefade": ["game/transforms.rpy", 436], "rightin": ["game/transforms.rpy", 97], "credits_text_scroll": ["game/credits.rpy", 226], "l43": ["game/transforms.rpy", 281], "l42": ["game/transforms.rpy", 279], "l41": ["game/transforms.rpy", 277], "l44": ["game/transforms.rpy", 283], "i33": ["game/transforms.rpy", 157], "i32": ["game/transforms.rpy", 155], "i31": ["game/transforms.rpy", 153], "s_kill_start": ["game/cgs.rpy", 319], "f11": ["game/transforms.rpy", 185], "paper_out": ["game/poems.rpy", 55], "l22": ["game/transforms.rpy", 293], "vignetteflicker": ["game/transforms.rpy", 453], "menu_logo_move": ["game/splash.rpy", 159], "dizzy": ["game/cgs.rpy", 330], "notify_appear": ["game/screens.rpy", 1578], "particle_fadeout": ["game/splash.rpy", 136], "ship": ["game/transforms.rpy", 22], "n_cg2_zoom": ["game/transforms.rpy", 334], "d11": ["game/transforms.rpy", 273], "i21": ["game/transforms.rpy", 159], "i22": ["game/transforms.rpy", 161], "credits_sticker_scroll": ["game/credits.rpy", 231], "h22": ["game/transforms.rpy", 227], "hop": ["game/transforms.rpy", 62], "rewind": ["game/transforms.rpy", 486], "panic": ["game/transforms.rpy", 80], "credits_scroll": ["game/credits.rpy", 221], "credits_text_scroll_left": ["game/credits.rpy", 249], "h32": ["game/transforms.rpy", 221], "h33": ["game/transforms.rpy", 223], "h31": ["game/transforms.rpy", 219], "n_cg2_wiggle_loop": ["game/transforms.rpy", 328], "d21": ["game/transforms.rpy", 269], "menu_bg_loop": ["game/splash.rpy", 151], "d22": ["game/transforms.rpy", 271], "i11": ["game/transforms.rpy", 163], "face": ["game/transforms.rpy", 299], "s22": ["game/transforms.rpy", 205], "s21": ["game/transforms.rpy", 203], "hf11": ["game/transforms.rpy", 251]}, "label": {"examplebattle": ["game/enemies/examplebattle.rpy", 7], "viewequipment": ["game/ship.rpy", 49], "warningscreen": ["game/splash.rpy", 444], "natsuki": ["game/hub.rpy", 125], "updateconsole_loop": ["game/console.rpy", 58], "autoload": ["game/splash.rpy", 491], "updateconsole": ["game/console.rpy", 32], "ch1s2": ["game/ch1.rpy", 41], "updateconsole_clearall": ["game/console.rpy", 45], "helpmenu": ["game/help.rpy", 13], "modendgameover": ["game/demoend.rpy", 18], "natsukimenu": ["game/hub.rpy", 138], "examplebattle2": ["game/enemies/examplebattle.rpy", 63], "impossible": ["game/enemies/impossible.rpy", 7], "ship": ["game/ship.rpy", 7], "ch1s1": ["game/ch1.rpy", 6], "sayori": ["game/hub.rpy", 87], "showpoem": ["game/poems.rpy", 153], "examplehostilebattle2": ["game/enemies/examplehostilebattle.rpy", 72], "quit": ["game/splash.rpy", 513], "examplehostilebattle": ["game/enemies/examplehostilebattle.rpy", 7], "playerturn": ["game/weapons.rpy", 41], "cantafford": ["game/shipstats.rpy", 141], "burst1": ["game/weapons.rpy", 107], "lcannon1": ["game/weapons.rpy", 134], "help": ["game/help.rpy", 6], "gameover": ["game/gameover.rpy", 6], "ch0_alt": ["game/ch0alt.rpy", 1], "ch1store1w": ["game/ch1-stores.rpy", 22], "start": ["game/script.rpy", 4], "stealth": ["game/weapons.rpy", 215], "ch1store1m": ["game/ch1-stores.rpy", 88], "shipmenu": ["game/ship.rpy", 14], "credits2": ["game/credits.rpy", 488], "enemyhlaser1": ["game/enemyattacks.rpyc", 7], "ch1s3": ["game/ch1.rpy", 118], "ch1store1e": ["game/ch1-stores.rpy", 55], "updateconsolehistory": ["game/console.rpy", 83], "impossible2": ["game/enemies/impossible.rpy", 75], "drawconsole": ["game/console.rpy", 76], "yurimenu": ["game/hub.rpy", 175], "viewweapons": ["game/ship.rpy", 34], "hub": ["game/hub.rpy", 7], "hideconsole": ["game/console.rpy", 94], "shipstats": ["game/ship.rpy", 29], "iplasma": ["game/enemyattacks.rpyc", 34], "ch1store1": ["game/ch1-stores.rpy", 7], "credits": ["game/credits.rpy", 396], "yuri": ["game/hub.rpy", 163], "modend": ["game/demoend.rpy", 6], "before_main_menu": ["game/splash.rpy", 509], "monika": ["game/hub.rpy", 26], "endgame": ["game/script.rpy", 47], "shipselect": ["game/shipselection.rpy", 65], "postcredits_loop": ["game/credits.rpy", 671], "after_load": ["game/splash.rpy", 476], "sayorimenu": ["game/hub.rpy", 100], "monikamenu": ["game/hub.rpy", 38], "artemis": ["game/weapons.rpy", 159], "ch0": ["game/ch0.rpy", 28], "intro": ["game/ch0.rpy", 5], "updateconsole_old": ["game/console.rpy", 51], "hcannon1": ["game/weapons.rpy", 187], "splashscreen": ["game/splash.rpy", 241], "halberd": ["game/weapons.rpy", 85]}}, "error": false, "size": [1280, 720], "build": {"documentation_patterns": ["README.html"], "directory_name": "DokiDokiStarCommander-1.0", "display_name": "Doki Doki Star Commander", "script_version": true, "destination": "DokiDokiStarCommander-1.0-dists", "renpy": false, "allow_integrated_gpu": true, "include_update": false, "base_patterns": [["*.py", null], ["*.sh", null], ["*.app/", null], ["*.dll", null], ["*.manifest", null], ["lib/", null], ["renpy/", null], ["update/", null], ["common/", null], ["update/", null], ["icon.ico", null], ["icon.icns", null], ["project.json", null], ["log.txt", null], ["errors.txt", null], ["traceback.txt", null], ["image_cache.txt", null], ["text_overflow.txt", null], ["dialogue.txt", null], ["dialogue.tab", null], ["profile_screen.txt", null], ["files.txt", null], ["tmp/", null], ["game/saves/", null], ["game/bytecode.rpyb", null], ["archived/", null], ["launcherinfo.py", null], ["android.txt", null], [".android.json", ["android"]], ["android-*.png", ["android"]], ["android-*.jpg", ["android"]], ["ouya_icon.png", null], ["ios-presplash.*", ["ios"]], ["ios-launchimage.png", null], ["ios-icon.png", null], ["web-presplash.png", ["web"]], ["web-presplash.jpg", ["web"]], ["game/mod_assets/**", ["mod_assets"]], ["game/**.rpyc", ["scripts"]], ["game/README.txt", null], ["game/**.txt", ["scripts"]], ["game/**.chr", ["scripts"]], ["game/advanced_scripts/**", ["scripts"]], ["**~", null], ["**.bak", null], ["**/.**", null], ["**/#**", null], ["**/thumbs.db", null], ["**.rpy", null], ["**.psd", null], ["**.sublime-project", null], ["**.sublime-workspace", null], ["/music/*.*", null], ["script-regex.txt", null], ["/game/10", null], ["/game/cache/*.*", null], ["**.rpa", null], ["README.html", ["DokiDokiStarCommander"]], ["ddmm-mod.json", ["DokiDokiStarCommander"]], [".*", null], ["**", ["all"]]], "version": "1.0", "archives": [["scripts", ["DokiDokiStarCommander"]], ["mod_assets", ["DokiDokiStarCommander"]]], "xbit_patterns": ["**.sh", "**/*.so.*", "**/*.so", "**/*.dylib", "lib/**/python", "lib/**/pythonw", "lib/**/zsync", "lib/**/zsyncmake", "**.app/Contents/MacOS/*", "**.app/Contents/MacOS/lib/**/python", "**.app/Contents/MacOS/lib/**/pythonw", "**.app/Contents/MacOS/lib/**/zsync", "**.app/Contents/MacOS/lib/**/zsyncmake"], "exclude_empty_directories": true, "renpy_patterns": [["renpy/common/_compat/**", null], ["renpy/common/_roundrect/**", null], ["renpy/common/_outline/**", null], ["renpy/common/_theme**", null], ["**~", null], ["**/#*", null], ["**/.*", null], ["**.old", null], ["**.new", null], ["**/*.pyc", null], ["renpy.py", ["all"]], ["renpy/", ["all"]], ["renpy/**.py", ["renpy"]], ["renpy/**.pyx", ["renpy"]], ["renpy/**.pyd", ["renpy"]], ["renpy/**.pxi", ["renpy"]], ["renpy/common/", ["all"]], ["renpy/common/_compat/**", ["renpy"]], ["renpy/common/**.rpy", ["renpy"]], ["renpy/common/**.rpym", ["renpy"]], ["renpy/common/_compat/**", ["renpy"]], ["renpy/common/**", ["all"]], ["renpy/**", ["all"]], ["lib/*/renpy", null], ["lib/*/renpy.exe", null], ["lib/windows-i686/**", ["windows"]], ["lib/linux-*/**", ["linux"]], ["lib/darwin-x86_64/**", ["mac"]], ["/lib/**", ["windows", "linux", "mac"]], ["renpy.sh", ["linux", "mac"]]], "packages": [{"dlc": false, "hidden": false, "description": "DDLC Compatible Mod", "formats": ["zip"], "file_lists": ["DokiDokiStarCommander"], "update": true, "name": "Mod"}], "executable_name": "DokiDokiStarCommander"}}